demo/mysql_setup.py
exec_engine/api_executor.py
exec_engine/db_manager.py
exec_engine/docker_sandbox.py
exec_engine/execution_engine.py
exec_engine/fs_manager.py
exec_engine/pipeline.py
exec_engine/server.py
exec_engine/utils.py
gorilla_x-0.1.2.dist-info/METADATA
gorilla_x-0.1.2.dist-info/WHEEL
gorilla_x-0.1.2.dist-info/top_level.txt
gorilla_x-0.1.2.dist-info/RECORD
